{"nodes": [{"string": "long;", "links": [], "variables": ["long"], "ids": [], "nodeId": 0, "featuresSelf": [], "operators": [], "constants": ["0", "0"], "features": []}, {"string": "scanf", "links": [], "variables": ["n"], "ids": [], "nodeId": 1, "featuresSelf": ["in"], "operators": ["&"], "constants": ["%lld,"], "features": []}, {"string": " i <= n ;", "links": [], "variables": ["n", "i"], "ids": [], "nodeId": 2, "featuresSelf": [], "operators": ["<="], "constants": ["1"], "features": []}, {"string": null, "links": [], "variables": [], "ids": [], "nodeId": 3, "featuresSelf": ["cn"], "operators": [], "constants": [], "features": []}, {"string": null, "links": [], "variables": ["i"], "ids": ["lp"], "nodeId": 4, "featuresSelf": [], "operators": ["++"], "constants": [], "features": []}, {"string": "scanf", "links": [], "variables": ["t"], "ids": ["lp"], "nodeId": 5, "featuresSelf": ["in"], "operators": ["&"], "constants": ["%lld,"], "features": []}, {"string": " s + i ;", "links": [], "variables": ["i", "s"], "ids": ["lp"], "nodeId": 6, "featuresSelf": [], "operators": ["+"], "constants": [], "features": []}, {"string": " a + t ;", "links": [], "variables": ["t", "a"], "ids": ["lp"], "nodeId": 7, "featuresSelf": [], "operators": ["+"], "constants": [], "features": []}, {"string": " s == a )", "links": [], "variables": ["a", "s"], "ids": [], "nodeId": 8, "featuresSelf": ["icn", "out", "out"], "operators": ["=="], "constants": ["YES)", "NO)"], "features": []}, {"string": " return 0 ;", "links": [], "variables": [], "ids": [], "nodeId": 9, "featuresSelf": ["return"], "operators": [], "constants": ["0"], "features": []}], "features": [{"controlContextEC": [":00", ":1;&;%lld,", ":2;<=;1", ":", "lp:1;++;", "lp:1;&;%lld,", "lp:2;+;", "lp:2;+;", ":2;==;YES)NO)", ":0"], "expr": ["00", "1;&;%lld,", "2;<=;1", "", "1;++;", "1;&;%lld,", "2;+;", "2;+;", "2;==;YES)NO)", "0"], "basic": ["0", "0", "&", "%lld,", "<=", "1", "loop", "++", "&", "%lld,", "+", "+", "==", "YES)", "NO)", "0"], "exprDepend": [], "controlContextBC": [":0", ":0", ":&", ":%lld,", ":<=", ":1", "lp:++", "lp:&", "lp:%lld,", "lp:+", "lp:+", ":==", ":YES)", ":NO)", ":0"]}]}