{"nodes": [{"string": " return __x ;", "links": [], "variables": ["__x"], "ids": [], "nodeId": 0, "featuresSelf": ["return"], "operators": [], "constants": [], "features": []}, {"string": " return __x ;", "links": [], "variables": ["__x"], "ids": [], "nodeId": 1, "featuresSelf": ["return"], "operators": [], "constants": [], "features": []}, {"string": " return __x ;", "links": [], "variables": ["__x"], "ids": [], "nodeId": 2, "featuresSelf": ["return"], "operators": [], "constants": [], "features": []}, {"string": "d;", "links": [], "variables": [], "ids": [], "nodeId": 3, "featuresSelf": [], "operators": [], "constants": [], "features": []}, {"string": " i < m - 1 ;", "links": [6, 7], "variables": [], "ids": [], "nodeId": 4, "featuresSelf": [], "operators": ["<"], "constants": ["0"], "features": []}, {"string": null, "links": [], "variables": [], "ids": [], "nodeId": 5, "featuresSelf": ["cn"], "operators": [], "constants": [], "features": []}, {"string": " m - 1 ;", "links": [], "variables": ["m"], "ids": [], "nodeId": 6, "featuresSelf": [], "operators": ["-"], "constants": ["1"], "features": []}, {"string": null, "links": [], "variables": ["i"], "ids": [], "nodeId": 7, "featuresSelf": [], "operators": [], "constants": [], "features": []}, {"string": null, "links": [], "variables": ["i"], "ids": ["lp"], "nodeId": 8, "featuresSelf": [], "operators": ["++"], "constants": [], "features": []}, {"string": " j < m ;", "links": [], "variables": ["i", "m", "j"], "ids": ["lp"], "nodeId": 9, "featuresSelf": [], "operators": ["+", "<"], "constants": ["1"], "features": []}, {"string": null, "links": [], "variables": [], "ids": ["lp"], "nodeId": 10, "featuresSelf": ["cn"], "operators": [], "constants": [], "features": []}, {"string": null, "links": [], "variables": ["j"], "ids": ["lp", "lp"], "nodeId": 11, "featuresSelf": [], "operators": ["++"], "constants": [], "features": []}, {"string": " ( abs ) ( a [ i ] - a [ j ] ) < d )", "links": [13, 14], "variables": [], "ids": ["lp", "lp"], "nodeId": 12, "featuresSelf": ["icn"], "operators": ["<"], "constants": [], "features": []}, {"string": null, "links": [], "variables": ["d"], "ids": ["lp", "lp"], "nodeId": 13, "featuresSelf": [], "operators": [], "constants": [], "features": []}, {"string": " a [ i ] - a [ j ] )", "links": [], "variables": ["a", "j", "i", "abs"], "ids": ["lp", "lp"], "nodeId": 14, "featuresSelf": [], "operators": ["-"], "constants": [], "features": []}, {"string": " a [ i ] - a [ j ] )", "links": [], "variables": ["a", "j", "i", "abs"], "ids": ["lp", "lp", "if"], "nodeId": 15, "featuresSelf": [], "operators": ["-"], "constants": [], "features": []}, {"string": " return d ;", "links": [], "variables": ["d"], "ids": [], "nodeId": 16, "featuresSelf": ["return"], "operators": [], "constants": [], "features": []}, {"string": "t;", "links": [], "variables": [], "ids": [], "nodeId": 17, "featuresSelf": [], "operators": [], "constants": [], "features": []}, {"string": "int a[5000];", "links": [], "variables": ["a"], "ids": [], "nodeId": 18, "featuresSelf": [], "operators": [], "constants": ["5000"], "features": []}, {"string": "scanf", "links": [], "variables": ["t"], "ids": [], "nodeId": 19, "featuresSelf": ["in"], "operators": ["&"], "constants": ["%d,"], "features": []}, {"string": " t > 0 )", "links": [], "variables": ["t"], "ids": [], "nodeId": 20, "featuresSelf": ["cn", "loop"], "operators": [">"], "constants": ["0"], "features": []}, {"string": "scanf", "links": [], "variables": ["m"], "ids": ["lp"], "nodeId": 21, "featuresSelf": ["in"], "operators": ["&"], "constants": ["%d,"], "features": []}, {"string": " i < m ;", "links": [], "variables": ["m", "i"], "ids": ["lp"], "nodeId": 22, "featuresSelf": [], "operators": ["<"], "constants": ["0"], "features": []}, {"string": null, "links": [], "variables": [], "ids": ["lp"], "nodeId": 23, "featuresSelf": ["cn"], "operators": [], "constants": [], "features": []}, {"string": null, "links": [], "variables": ["i"], "ids": ["lp", "lp"], "nodeId": 24, "featuresSelf": [], "operators": ["++"], "constants": [], "features": []}, {"string": "scanf", "links": [], "variables": ["a", "i"], "ids": ["lp", "lp"], "nodeId": 25, "featuresSelf": ["in"], "operators": ["&"], "constants": ["%d,"], "features": []}, {"string": " k = diff ( a , m ) ;", "links": [], "variables": ["a", "m", "diff"], "ids": ["lp"], "nodeId": 26, "featuresSelf": [], "operators": [], "constants": [], "features": []}, {"string": "printf", "links": [], "variables": ["k"], "ids": ["lp"], "nodeId": 27, "featuresSelf": ["out"], "operators": [], "constants": ["%d\\n,"], "features": []}, {"string": " t -- ;", "links": [], "variables": ["t"], "ids": ["lp"], "nodeId": 28, "featuresSelf": [], "operators": ["--"], "constants": [], "features": []}, {"string": " return 0 ;", "links": [], "variables": [], "ids": [], "nodeId": 29, "featuresSelf": ["return"], "operators": [], "constants": ["0"], "features": []}], "features": [{"controlContextEC": [":", ":", ":", ":", ":", ":", ":", ":", ":", ":", ":0;<;0", ":", ":1;-;1", ":", "lp:1;++;", "lp:3;+;3;<;1", "lp:", "lplp:1;++;", "lplp:0;<;", "lplp:", "lplp:4;-;", "lplpif:4;-;", ":", ":", ":", ":", ":", ":0;<;0", ":", ":1;-;1", ":", "lp:1;++;", "lp:3;+;3;<;1", "lp:", "lplp:1;++;", "lplp:0;<;", "lplp:", "lplp:4;-;", "lplpif:4;-;", ":", ":", ":5000", ":1;&;%d,", ":1;>;0", "lp:1;&;%d,", "lp:2;<;0", "lp:", "lplp:1;++;", "lplp:2;&;%d,", "lp:", "lp:%d\\n,", "lp:1;--;", ":0"], "expr": ["", "", "", "", "", "", "", "", "", "", "0;<;0", "", "1;-;1", "", "1;++;", "3;+;3;<;1", "", "1;++;", "0;<;", "", "4;-;", "4;-;", "", "", "", "", "", "0;<;0", "", "1;-;1", "", "1;++;", "3;+;3;<;1", "", "1;++;", "0;<;", "", "4;-;", "4;-;", "", "", "5000", "1;&;%d,", "1;>;0", "1;&;%d,", "2;<;0", "", "1;++;", "2;&;%d,", "", "%d\\n,", "1;--;", "0"], "basic": ["<", "0", "loop", "-", "1", "++", "+", "<", "1", "loop", "++", "<", "-", "-", "<", "0", "loop", "-", "1", "++", "+", "<", "1", "loop", "++", "<", "-", "-", "5000", "&", "%d,", ">", "0", "loop", "&", "%d,", "<", "0", "loop", "++", "&", "%d,", "%d\\n,", "--", "0"], "exprDepend": ["#4;-;", "#4;-;", "#2;<;0", "1;++;#2;<;0", "3;+;3;<;1#2;<;0", "4;-;#2;<;0", "4;-;#2;<;0"], "controlContextBC": [":<", ":0", ":-", ":1", "lp:++", "lp:+", "lp:<", "lp:1", "lplp:++", "lplp:<", "lplp:-", "lplpif:-", ":<", ":0", ":-", ":1", "lp:++", "lp:+", "lp:<", "lp:1", "lplp:++", "lplp:<", "lplp:-", "lplpif:-", ":5000", ":&", ":%d,", ":>", ":0", "lp:&", "lp:%d,", "lp:<", "lp:0", "lplp:++", "lplp:&", "lplp:%d,", "lp:%d\\n,", "lp:--", ":0"]}]}