{"nodes": [{"string": "n;", "links": [], "variables": [], "ids": [], "nodeId": 0, "featuresSelf": [], "operators": [], "constants": [], "features": []}, {"string": "space;", "links": [], "variables": [], "ids": [], "nodeId": 1, "featuresSelf": [], "operators": [], "constants": [], "features": []}, {"string": "char a[315];", "links": [], "variables": ["a"], "ids": [], "nodeId": 2, "featuresSelf": [], "operators": [], "constants": ["315"], "features": []}, {"string": "scanf", "links": [], "variables": ["n"], "ids": [], "nodeId": 3, "featuresSelf": ["in"], "operators": ["&"], "constants": ["%d,"], "features": []}, {"string": "scanf", "links": [], "variables": ["space"], "ids": [], "nodeId": 4, "featuresSelf": ["in"], "operators": ["&"], "constants": ["%c,"], "features": []}, {"string": " n > 0 )", "links": [], "variables": ["n"], "ids": [], "nodeId": 5, "featuresSelf": ["cn", "loop"], "operators": [">"], "constants": ["0"], "features": []}, {"string": "i;", "links": [], "variables": ["i"], "ids": ["lp"], "nodeId": 6, "featuresSelf": [], "operators": [], "constants": ["0", "0", "0", "0"], "features": []}, {"string": "gets", "links": [], "variables": ["a"], "ids": ["lp"], "nodeId": 7, "featuresSelf": ["in"], "operators": [], "constants": [], "features": []}, {"string": " l = strlen ( a ) ;", "links": [], "variables": ["a", "strlen"], "ids": ["lp"], "nodeId": 8, "featuresSelf": [], "operators": [], "constants": [], "features": []}, {"string": " i < 91 ;", "links": [], "variables": ["i"], "ids": ["lp"], "nodeId": 9, "featuresSelf": [], "operators": ["<"], "constants": ["65", "91"], "features": []}, {"string": null, "links": [], "variables": [], "ids": ["lp"], "nodeId": 10, "featuresSelf": ["cn"], "operators": [], "constants": [], "features": []}, {"string": null, "links": [], "variables": ["i"], "ids": ["lp", "lp"], "nodeId": 11, "featuresSelf": [], "operators": ["++"], "constants": [], "features": []}, {"string": " alph = i ;", "links": [], "variables": ["i"], "ids": ["lp", "lp"], "nodeId": 12, "featuresSelf": [], "operators": [], "constants": [], "features": []}, {"string": " i + 32 ;", "links": [], "variables": ["i"], "ids": ["lp", "lp"], "nodeId": 13, "featuresSelf": [], "operators": ["+"], "constants": ["32"], "features": []}, {"string": " j < l ;", "links": [], "variables": ["l", "j"], "ids": ["lp", "lp"], "nodeId": 14, "featuresSelf": [], "operators": ["<"], "constants": ["0"], "features": []}, {"string": null, "links": [], "variables": [], "ids": ["lp", "lp"], "nodeId": 15, "featuresSelf": ["cn"], "operators": [], "constants": [], "features": []}, {"string": null, "links": [], "variables": ["j"], "ids": ["lp", "lp", "lp"], "nodeId": 16, "featuresSelf": [], "operators": ["++"], "constants": [], "features": []}, {"string": " alph == a [ j ] ||", "links": [], "variables": ["a", "j", "alph2", "alph"], "ids": ["lp", "lp", "lp"], "nodeId": 17, "featuresSelf": ["icn"], "operators": ["||", "==", "=="], "constants": [], "features": []}, {"string": " break ;", "links": [], "variables": [], "ids": ["lp", "lp", "lp", "if"], "nodeId": 18, "featuresSelf": ["break"], "operators": [], "constants": [], "features": []}, {"string": " j == l )", "links": [], "variables": ["l", "j"], "ids": ["lp", "lp"], "nodeId": 19, "featuresSelf": ["icn"], "operators": ["=="], "constants": [], "features": []}, {"string": " fl = 1 ;", "links": [], "variables": [], "ids": ["lp", "lp", "if"], "nodeId": 20, "featuresSelf": [], "operators": [], "constants": ["1"], "features": []}, {"string": " break ;", "links": [], "variables": [], "ids": ["lp", "lp", "if"], "nodeId": 21, "featuresSelf": ["break"], "operators": [], "constants": [], "features": []}, {"string": " fl == 1 )", "links": [], "variables": ["fl", "alph"], "ids": ["lp"], "nodeId": 22, "featuresSelf": ["icn", "out", "out"], "operators": ["=="], "constants": ["1", "%c\\n,", "~\\n)"], "features": []}, {"string": " n -- ;", "links": [], "variables": ["n"], "ids": ["lp"], "nodeId": 23, "featuresSelf": [], "operators": ["--"], "constants": [], "features": []}, {"string": " return 0 ;", "links": [], "variables": [], "ids": [], "nodeId": 24, "featuresSelf": ["return"], "operators": [], "constants": ["0"], "features": []}], "features": [{"controlContextEC": [":", ":", ":315", ":1;&;%d,", ":1;&;%c,", ":1;>;0", "lp:0000", "lp:", "lp:", "lp:1;<;6591", "lp:", "lplp:1;++;", "lplp:", "lplp:1;+;32", "lplp:2;<;0", "lplp:", "lplplp:1;++;", "lplplp:4;||;4;==;4;==;", "lplplpif:", "lplp:2;==;", "lplpif:1", "lplpif:", "lp:2;==;1%c\\n,~\\n)", "lp:1;--;", ":0"], "expr": ["", "", "315", "1;&;%d,", "1;&;%c,", "1;>;0", "0000", "", "", "1;<;6591", "", "1;++;", "", "1;+;32", "2;<;0", "", "1;++;", "4;||;4;==;4;==;", "", "2;==;", "1", "", "2;==;1%c\\n,~\\n)", "1;--;", "0"], "basic": ["315", "&", "%d,", "&", "%c,", ">", "0", "loop", "0", "0", "0", "0", "<", "65", "91", "loop", "++", "+", "32", "<", "0", "loop", "++", "||", "==", "==", "==", "1", "==", "1", "%c\\n,", "~\\n)", "--", "0"], "exprDepend": ["0000#1;<;6591"], "controlContextBC": [":315", ":&", ":%d,", ":&", ":%c,", ":>", ":0", "lp:0", "lp:0", "lp:0", "lp:0", "lp:<", "lp:65", "lp:91", "lplp:++", "lplp:+", "lplp:32", "lplp:<", "lplp:0", "lplplp:++", "lplplp:||", "lplplp:==", "lplplp:==", "lplp:==", "lplpif:1", "lp:==", "lp:1", "lp:%c\\n,", "lp:~\\n)", "lp:--", ":0"]}]}